bioos/__about__.py
bioos/__init__.py
bioos/bioos.py
bioos/bioos_workflow.py
bioos/bw_import.py
bioos/bw_import_status_check.py
bioos/bw_status_check.py
bioos/config.py
bioos/errors.py
bioos/get_submission_logs.py
bioos/log.py
bioos/workflow_info.py
bioos/internal/__init__.py
bioos/internal/tos.py
bioos/models/__init__.py
bioos/models/models.py
bioos/resource/__init__.py
bioos/resource/data_models.py
bioos/resource/files.py
bioos/resource/iesapp.py
bioos/resource/utility.py
bioos/resource/workflows.py
bioos/resource/workspaces.py
bioos/service/BioOsService.py
bioos/service/__init__.py
bioos/service/api.py
bioos/service/config.py
bioos/tests/__init__.py
bioos/tests/base.py
bioos/tests/bioos.py
bioos/tests/data_models.py
bioos/tests/files.py
bioos/tests/utils.py
bioos/tests/workflows.py
bioos/tests/workspaces.py
bioos/utils/__init__.py
bioos/utils/common_tools.py
bioos/utils/workflows.py
pybioos-0.0.19.dist-info/LICENSE
pybioos-0.0.19.dist-info/METADATA
pybioos-0.0.19.dist-info/WHEEL
pybioos-0.0.19.dist-info/entry_points.txt
pybioos-0.0.19.dist-info/top_level.txt
pybioos-0.0.19.dist-info/RECORD
