Metadata-Version: 2.1
Name: pybioos
Version: 0.0.19
Summary: BioOS SDK for Python
Home-page: https://github.com/GBA-BI/pybioos
Author: Jilong Liu
Author-email: liu_jilong@gzlab.ac.cn
License: MIT Licence
Keywords: pip,bioos
Platform: any
Classifier: Programming Language :: Python :: 3
Classifier: Intended Audience :: Science/Research
Classifier: Topic :: Scientific/Engineering :: Bio-Informatics
Classifier: Topic :: Scientific/Engineering :: Interface Engine/Protocol Translator
License-File: LICENSE
Requires-Dist: volcengine (>=1.0.61)
Requires-Dist: tabulate (>=0.8.10)
Requires-Dist: click (>=8.0.0)
Requires-Dist: pandas (>=1.3.0)
Requires-Dist: tos (==2.5.6)
Requires-Dist: cachetools (>=5.2.0)
Requires-Dist: typing-extensions (>=4.4.0)
Requires-Dist: apscheduler (>=3.10.4)
Requires-Dist: colorama (>=0.4.6)
